sift/__init__.py
sift/case_study.py
sift/chaos_monkey/__init__.py
sift/chaos_monkey/polluter.py
sift/cli.py
sift/core/__init__.py
sift/core/benchmark.py
sift/core/inference.py
sift/core/models.py
sift/core/profiler.py
sift/core/synthesizer.py
sift/dashboard.py
sift/scorecard.py
sift_dqe-0.1.1.dist-info/entry_points.txt
sift_dqe-0.1.1.dist-info/METADATA
sift_dqe-0.1.1.dist-info/WHEEL
sift_dqe-0.1.1.dist-info/RECORD
