Metadata-Version: 2.4
Name: sift-dqe
Version: 0.1.1
Summary: An adaptive data quality engine that detects anomalies and suggests fixes.
License: MIT
Author: Pranav Kandpal
Requires-Python: >=3.10,<3.12
Classifier: License :: OSI Approved :: MIT License
Classifier: Programming Language :: Python :: 3
Classifier: Programming Language :: Python :: 3.10
Classifier: Programming Language :: Python :: 3.11
Requires-Dist: numpy (>=1.26.0,<2.0.0)
Requires-Dist: polars (>=1.0.0,<2.0.0)
Requires-Dist: pydantic (>=2.0.0,<3.0.0)
Requires-Dist: rich (>=13.0.0,<14.0.0)
Requires-Dist: scikit-learn (>=1.5.0,<2.0.0)
Requires-Dist: scipy (>=1.10.0,<2.0.0)
Requires-Dist: typer (>=0.9.0,<0.10.0)
